edstem/__init__.py
edstem/api/__init__.py
edstem/api/edstem.py
edstem-0.0.1.dist-info/LICENSE
edstem-0.0.1.dist-info/WHEEL
edstem-0.0.1.dist-info/METADATA
edstem-0.0.1.dist-info/RECORD
