Metadata-Version: 2.1
Name: edstem
Version: 0.0.1
Summary: A 3rd-party Python wrapper for the (unofficial) EdStem API. Not maintained by EdStem staff.
License: MIT
Author: Hunter Schafer
Author-email: hunterschafer@gmail.com
Requires-Python: >=3.8,<4.0
Classifier: License :: OSI Approved :: MIT License
Classifier: Programming Language :: Python :: 3
Classifier: Programming Language :: Python :: 3.8
Classifier: Programming Language :: Python :: 3.9
Classifier: Programming Language :: Python :: 3.10
Requires-Dist: requests (>=2.30.0,<3.0.0)
